dida365/__init__.py
dida365/auth.py
dida365/client.py
dida365/config.py
dida365/exceptions.py
dida365/http.py
dida365/logger.py
dida365/settings.py
dida365/models/base.py
dida365/models/project.py
dida365/models/task.py
dida365-0.1.9.dist-info/METADATA
dida365-0.1.9.dist-info/WHEEL
dida365-0.1.9.dist-info/licenses/LICENSE
dida365-0.1.9.dist-info/RECORD
