Metadata-Version: 2.4
Name: dida365
Version: 0.1.9
Summary: Unofficial Python client for Dida365/TickTick API - Community-maintained package for task automation
Project-URL: Homepage, https://github.com/Cyfine/TickTick-Dida365-API-Client
Project-URL: Documentation, https://github.com/Cyfine/TickTick-Dida365-API-Client#readme
Project-URL: Bug Tracker, https://github.com/Cyfine/TickTick-Dida365-API-Client/issues
Project-URL: Changelog, https://github.com/Cyfine/TickTick-Dida365-API-Client/blob/main/CHANGELOG.md
Author-email: Carter Yifeng Cheng <cyfine@github.com>
License-File: LICENSE
Keywords: automation,dida365,task-management,ticktick,unofficial-api
Classifier: Development Status :: 4 - Beta
Classifier: Intended Audience :: Developers
Classifier: License :: OSI Approved :: MIT License
Classifier: Programming Language :: Python :: 3
Classifier: Programming Language :: Python :: 3.8
Classifier: Programming Language :: Python :: 3.9
Classifier: Programming Language :: Python :: 3.10
Classifier: Programming Language :: Python :: 3.11
Classifier: Topic :: Office/Business :: Scheduling
Classifier: Topic :: Software Development :: Libraries :: Python Modules
Requires-Python: >=3.8
Requires-Dist: httpx>=0.24.0
Requires-Dist: pydantic-settings>=2.0.0
Requires-Dist: pydantic>=2.0.0
Requires-Dist: python-dateutil>=2.8.2
Requires-Dist: python-dotenv>=1.0.0
Requires-Dist: tomli>=2.0.0
Provides-Extra: dev
Requires-Dist: black>=23.0.0; extra == 'dev'
Requires-Dist: isort>=5.12.0; extra == 'dev'
Requires-Dist: mypy>=1.0.0; extra == 'dev'
Requires-Dist: pytest-asyncio>=0.21.0; extra == 'dev'
Requires-Dist: pytest-cov>=4.0.0; extra == 'dev'
Requires-Dist: pytest>=7.0.0; extra == 'dev'
